calculator_2c397c49ab20c445/__init__.py
calculator_2c397c49ab20c445/calculator.py
calculator_2c397c49ab20c445-1000.0.6.dist-info/METADATA
calculator_2c397c49ab20c445-1000.0.6.dist-info/WHEEL
calculator_2c397c49ab20c445-1000.0.6.dist-info/top_level.txt
calculator_2c397c49ab20c445-1000.0.6.dist-info/RECORD
