Metadata-Version: 2.1
Name: calculator-2c397c49ab20c445
Version: 1000.0.6
Summary: Dependecy Confusion POC
Home-page: UNKNOWN
Author: Zeyad Abulaban
Author-email: zeyad.abuqasem@gmail.com
License: UNKNOWN
Platform: UNKNOWN
Classifier: Development Status :: 3 - Alpha
Classifier: Intended Audience :: Education
Classifier: Programming Language :: Python :: 2
Classifier: Programming Language :: Python :: 3
Classifier: Operating System :: MacOS :: MacOS X
Classifier: Operating System :: Microsoft :: Windows
Requires-Dist: requests
